proxyChecker/__init__.py
proxyChecker/proxyCheck.py
proxyChecker/proxyCheck_process.py
proxyChecker/userAgentData.py
proxyCheck_mp-0.3.0.dist-info/LICENCE
proxyCheck_mp-0.3.0.dist-info/METADATA
proxyCheck_mp-0.3.0.dist-info/WHEEL
proxyCheck_mp-0.3.0.dist-info/top_level.txt
proxyCheck_mp-0.3.0.dist-info/RECORD
