Metadata-Version: 2.1
Name: proxyCheck-mp
Version: 0.3.0
Summary: You can check the availability of the proxy.
Home-page: https://github.com/IMaresaLI/Proxy_Checker
Author: Batuhan Olgac
Author-email: mares4l@hotmail.com
License: MIT
Project-URL: Bug Tracker, https://github.com/IMaresaLI/Proxy_Checker/issues
Classifier: Programming Language :: Python :: 3
Classifier: Programming Language :: Python :: 3.5
Classifier: Programming Language :: Python :: 3.6
Classifier: Programming Language :: Python :: 3.7
Classifier: Programming Language :: Python :: 3.8
Classifier: Programming Language :: Python :: 3.9
Classifier: License :: OSI Approved :: MIT License
Classifier: Operating System :: Unix
Classifier: Operating System :: POSIX
Classifier: Operating System :: Microsoft :: Windows
Requires-Python: >=3
License-File: LICENCE
Requires-Dist: requests
Requires-Dist: requests[socks]
Requires-Dist: syscolors
